Metadata-Version: 1.2
Name: sqgtool
Version: 0.0.5.dev3
Summary: Classification of stars, quasars, and galaxies in S-PLUS
Home-page: http://github.com/marixko/sqgtool
Author: Lilianne Nakazono
Author-email: lilianne.nakazono@usp.br
License: MIT
Platform: UNKNOWN
Classifier: Development Status :: 3 - Alpha
Classifier: Programming Language :: Python :: 3
Classifier: Intended Audience :: Science/Research
Classifier: Topic :: Scientific/Engineering :: Astronomy
Requires-Python: >=3
